nginx_krbauth.py
nginx_krbauth-0.0.4.dist-info/LICENSE
nginx_krbauth-0.0.4.dist-info/METADATA
nginx_krbauth-0.0.4.dist-info/WHEEL
nginx_krbauth-0.0.4.dist-info/top_level.txt
nginx_krbauth-0.0.4.dist-info/RECORD
