Metadata-Version: 2.1
Name: nginx_krbauth
Version: 0.0.4
Summary: LDAP + Kerberos authenticator for nginx's auth_request module.
Home-page: https://github.com/quantum5/nginx-krbauth
Author: quantum
Author-email: quantum2048@gmail.com
Keywords: ldap kerberos nginx
Classifier: Development Status :: 4 - Beta
Classifier: Environment :: Web Environment
Classifier: Framework :: Flask
Classifier: Intended Audience :: System Administrators
Classifier: License :: OSI Approved :: MIT License
Classifier: Operating System :: POSIX :: Linux
Classifier: Programming Language :: Python
Classifier: Programming Language :: Python :: 3
Classifier: Programming Language :: Python :: 3.9
Classifier: Programming Language :: Python :: 3.10
Classifier: Programming Language :: Python :: 3.11
Classifier: Programming Language :: Python :: 3.12
Classifier: Programming Language :: Python :: 3.13
Classifier: Topic :: Internet :: WWW/HTTP :: HTTP Servers
Classifier: Topic :: Internet :: WWW/HTTP :: WSGI :: Application
Classifier: Topic :: Security
Classifier: Topic :: System :: Systems Administration :: Authentication/Directory :: LDAP
License-File: LICENSE
Requires-Dist: flask
Requires-Dist: gssapi
Requires-Dist: python-ldap
